puddleglum-0.1.1.dist-info/METADATA
puddleglum-0.1.1.dist-info/WHEEL
puddleglum/__init__.py
puddleglum/puddleglum.cpython-39-aarch64-linux-gnu.so
puddleglum-0.1.1.dist-info/RECORD
