Metadata-Version: 2.3
Name: puddleglum
Version: 0.1.1
